{"cameraMode":{"drawMode":0,"name":"Shaded","section":"Shading Mode"},"sceneLighting":true,"audioPlay":false,"sceneViewState":{"showFog":true,"showMaterialUpdate":false,"showSkybox":true,"showFlares":true,"showImageEffects":true,"showParticleSystems":true},"in2DMode":false,"pivot":{"x":-0.39999985694885256,"y":1.0283616781234742,"z":-0.024880141019821168},"rotation":{"x":0.02618318609893322,"y":0.9715467691421509,"z":-0.1967497020959854,"w":0.12929171323776246},"size":1.1374605894088746,"orthographic":false}